{
  "id": 10015,
  "name": "帝隆",
  "nick": "努力的炎拳使",
  "head": "07_pic_27",
  "draw": "dillon",
  "crystal": {
    "black": [
      {
        "name": "焚身裁决",
        "crystals": {
          "top": [
            [
              5012,
              3
            ],
            [
              5013,
              3
            ]
          ],
          "mid": [
            [
              5006,
              2
            ]
          ],
          "bot": [
            [
              5002,
              1
            ],
            [
              5003,
              1
            ]
          ]
        },
        "texts": [
          "<span style=\"color:#DC6727\">9级</span>：炎拳会额外附带1层灼烧效果。"
        ],
        "level": 1
      },
      {
        "name": "撼世禁咒",
        "crystals": {
          "top": [
            [
              5012,
              0
            ],
            [
              5013,
              0
            ]
          ],
          "mid": [
            [
              5006,
              0
            ]
          ],
          "bot": [
            [
              5015,
              2
            ],
            [
              5016,
              2
            ]
          ]
        },
        "texts": [
          "<span style=\"color:#DC6727\">8级</span>：炎拳会额外附带2层灼烧效果。",
          "<span style=\"color:#DC6727\">9级</span>：自身175距离内的敌方目标所受伤害提升<span style=\"color:rgb(75, 164, 70)\">10%</span>。"
        ],
        "level": 2
      },
      {
        "name": "束缚禁制",
        "crystals": {
          "top": [
            [
              5012,
              0
            ],
            [
              5013,
              0
            ]
          ],
          "bot": [
            [
              5015,
              0
            ],
            [
              5016,
              0
            ]
          ],
          "mid": [
            [
              5017,
              1
            ]
          ]
        },
        "states": [
          "<span style=\"color:#DC6727\">7级（额外）</span>：生命增加 120000",
          "<span style=\"color:#DC6727\">8级（额外）</span>：攻击力 13000 "
        ],
        "level": 3
      }
    ],
    "white": [
      {
        "name": "入圣献身",
        "crystals": {
          "top": [
            [
              5030,
              3
            ],
            [
              5031,
              3
            ]
          ],
          "mid": [
            [
              5024,
              2
            ]
          ],
          "bot": [
            [
              5020,
              1
            ],
            [
              5021,
              1
            ]
          ]
        },
        "texts": [
          "<span style=\"color:#DC6727\">9级</span>：赤红斗气的治疗量额外增加<span style=\"color:rgb(75, 164, 70)\">5%</span>最大生命值。"
        ],
        "level": 1
      },
      {
        "name": "救世圣战",
        "crystals": {
          "top": [
            [
              5030,
              0
            ],
            [
              5031,
              0
            ]
          ],
          "mid": [
            [
              5024,
              0
            ]
          ],
          "bot": [
            [
              5033,
              2
            ],
            [
              5034,
              2
            ]
          ]
        },
        "texts": [
          "<span style=\"color:#DC6727\">8级</span>：赤红斗气的治疗量额外增加<span style=\"color:rgb(75, 164, 70)\">10%</span>最大生命值。",
          "<span style=\"color:#DC6727\">9级</span>：当自身处于最前排时，会赋予其他全部友军<span style=\"color:rgb(75, 164, 70)\">20%</span>的自身基础防御力。"
        ],
        "level": 2
      },
      {
        "name": "炎帝",
        "crystals": {
          "top": [
            [
              5030,
              0
            ],
            [
              5031,
              0
            ]
          ],
          "bot": [
            [
              5033,
              0
            ],
            [
              5034,
              0
            ]
          ],
          "mid": [
            [
              5035,
              1
            ]
          ]
        },
        "states": [
          "<span style=\"color:#DC6727\">7级（额外）</span>：生命增加 120000",
          "<span style=\"color:#DC6727\">8级（额外）</span>：防御力 13000 "
        ],
        "level": 3
      }
    ],
    "blackSpan": {
      "1": [],
      "2": []
    },
    "whiteSpan": {
      "1": [],
      "2": []
    }
  }
}