{
  "id": 10056,
  "name": "艾德蕾妮",
  "nick": "永夜的执灯者",
  "head": "07_pic_170",
  "draw": "edelenyi",
  "crystal": {
    "black": [
      {
        "name": "送葬者",
        "crystals": {
          "top": [
            [
              5010,
              3
            ],
            [
              5011,
              3
            ]
          ],
          "mid": [
            [
              5007,
              2
            ]
          ],
          "bot": [
            [
              5003,
              1
            ],
            [
              5004,
              1
            ]
          ]
        },
        "texts": [
          "<span style=\"color:#DC6727\">9级</span>：艾德蕾妮的无懈可击可以抵挡自身<span style=\"color:rgb(75, 164, 70)\">60%</span>攻击力以下的伤害值。"
        ],
        "level": 1
      },
      {
        "name": "冥界执刑人",
        "crystals": {
          "top": [
            [
              5010,
              0
            ],
            [
              5011,
              0
            ]
          ],
          "mid": [
            [
              5007,
              0
            ]
          ],
          "bot": [
            [
              5016,
              2
            ],
            [
              5017,
              2
            ]
          ]
        },
        "texts": [
          "<span style=\"color:#DC6727\">8级</span>：艾德蕾妮的无懈可击可以抵挡自身<span style=\"color:rgb(75, 164, 70)\">70%</span>攻击力以下的伤害值。",
          "<span style=\"color:#DC6727\">9级</span>：自身175距离内的敌方目标所受伤害提升<span style=\"color:rgb(75, 164, 70)\">10%</span>。"
        ],
        "level": 2
      },
      {
        "name": "赐死之剑",
        "crystals": {
          "top": [
            [
              5010,
              0
            ],
            [
              5011,
              0
            ]
          ],
          "bot": [
            [
              5016,
              0
            ],
            [
              5017,
              0
            ]
          ],
          "mid": [
            [
              5018,
              1
            ]
          ]
        },
        "states": [
          "<span style=\"color:#DC6727\">7级（额外）</span>：生命增加 120000",
          "<span style=\"color:#DC6727\">8级（额外）</span>：攻击力 13000 "
        ],
        "level": 3
      }
    ],
    "white": [
      {
        "name": "安息之刃",
        "crystals": {
          "top": [
            [
              5028,
              3
            ],
            [
              5029,
              3
            ]
          ],
          "mid": [
            [
              5025,
              2
            ]
          ],
          "bot": [
            [
              5021,
              1
            ],
            [
              5022,
              1
            ]
          ]
        },
        "texts": [
          "<span style=\"color:#DC6727\">9级</span>：幽魂之灯赋予的护盾增加艾德蕾妮<span style=\"color:rgb(75, 164, 70)\">100%</span>的攻击力的护盾值。"
        ],
        "level": 1
      },
      {
        "name": "冥王侍从",
        "crystals": {
          "top": [
            [
              5028,
              0
            ],
            [
              5029,
              0
            ]
          ],
          "mid": [
            [
              5025,
              0
            ]
          ],
          "bot": [
            [
              5034,
              2
            ],
            [
              5035,
              2
            ]
          ]
        },
        "texts": [
          "<span style=\"color:#DC6727\">8级</span>：幽魂之灯赋予的护盾增加艾德蕾妮<span style=\"color:rgb(75, 164, 70)\">200%</span>的攻击力的护盾值。",
          "<span style=\"color:#DC6727\">9级</span>：当自身处于最前排时，会赋予其他全部友军<span style=\"color:rgb(75, 164, 70)\">20%</span>的自身基础防御力。"
        ],
        "level": 2
      },
      {
        "name": "审判之剑",
        "crystals": {
          "top": [
            [
              5028,
              0
            ],
            [
              5029,
              0
            ]
          ],
          "bot": [
            [
              5034,
              0
            ],
            [
              5035,
              0
            ]
          ],
          "mid": [
            [
              5036,
              1
            ]
          ]
        },
        "states": [
          "<span style=\"color:#DC6727\">7级（额外）</span>：生命增加 120000",
          "<span style=\"color:#DC6727\">8级（额外）</span>：防御力 13000 "
        ],
        "level": 3
      }
    ],
    "blackSpan": {
      "1": [],
      "2": []
    },
    "whiteSpan": {
      "1": [],
      "2": []
    }
  }
}