{
  "id": 10120,
  "name": "提亚马特",
  "nick": "龙之谶纬",
  "head": "07_pic_tiamat",
  "draw": "tiamat",
  "crystal": {
    "black": [
      {
        "name": "谶纬之龙",
        "crystals": {
          "top": [
            [
              5009,
              3
            ],
            [
              5011,
              3
            ]
          ],
          "mid": [
            [
              5007,
              2
            ]
          ],
          "bot": [
            [
              5003,
              1
            ],
            [
              5005,
              1
            ]
          ]
        },
        "texts": [
          "<span style=\"color:#DC6727\">9级</span>：谶纬龙陨的伤害提升<span style=\"color:rgb(75, 164, 70)\">20%</span>。"
        ],
        "level": 1
      },
      {
        "name": "零碎语屑",
        "crystals": {
          "top": [
            [
              5009,
              0
            ],
            [
              5011,
              0
            ]
          ],
          "mid": [
            [
              5007,
              0
            ]
          ],
          "bot": [
            [
              5015,
              2
            ],
            [
              5018,
              2
            ]
          ]
        },
        "texts": [
          "<span style=\"color:#DC6727\">8级</span>：谶纬龙陨的伤害提升<span style=\"color:rgb(75, 164, 70)\">40%</span>。",
          "<span style=\"color:#DC6727\">9级</span>：每过6秒提升自身的输出伤害<span style=\"color:rgb(75, 164, 70)\">5%</span>，可叠加<span style=\"color:rgb(75, 164, 70)\">6</span>层。"
        ],
        "level": 2
      },
      {
        "name": "龙之脊尾",
        "crystals": {
          "top": [
            [
              5009,
              0
            ],
            [
              5011,
              0
            ]
          ],
          "bot": [
            [
              5015,
              0
            ],
            [
              5018,
              0
            ]
          ],
          "mid": [
            [
              5016,
              1
            ]
          ]
        },
        "states": [
          "<span style=\"color:#DC6727\">7级（额外）</span>：生命增加 120000",
          "<span style=\"color:#DC6727\">8级（额外）</span>：攻击力 13000 "
        ],
        "level": 3
      }
    ],
    "white": [
      {
        "name": "苍白绘色",
        "crystals": {
          "top": [
            [
              5027,
              3
            ],
            [
              5029,
              3
            ]
          ],
          "mid": [
            [
              5025,
              2
            ]
          ],
          "bot": [
            [
              5021,
              1
            ],
            [
              5023,
              1
            ]
          ]
        },
        "texts": [
          "<span style=\"color:#DC6727\">9级</span>：灭世预言释放时，额外提供<span style=\"color:rgb(75, 164, 70)\">1</span>层<span style=\"color:rgb(220, 103, 39)\">风言</span>。"
        ],
        "level": 1
      },
      {
        "name": "开疆拓土",
        "crystals": {
          "top": [
            [
              5027,
              0
            ],
            [
              5029,
              0
            ]
          ],
          "mid": [
            [
              5025,
              0
            ]
          ],
          "bot": [
            [
              5033,
              2
            ],
            [
              5036,
              2
            ]
          ]
        },
        "texts": [
          "<span style=\"color:#DC6727\">8级</span>：灭世预言释放时，额外提供<span style=\"color:rgb(75, 164, 70)\">2</span>层<span style=\"color:rgb(220, 103, 39)\">风言</span>。",
          "<span style=\"color:#DC6727\">9级</span>：自身获得基础<span style=\"color:rgb(75, 164, 70)\">5%</span>所受伤害降低，同时自身所受伤害的<span style=\"color:rgb(75, 164, 70)\">30%</span>会在随后的<span style=\"color:rgb(75, 164, 70)\">3</span>秒内持续扣除。"
        ],
        "level": 2
      },
      {
        "name": "死亡之渊",
        "crystals": {
          "top": [
            [
              5027,
              0
            ],
            [
              5029,
              0
            ]
          ],
          "bot": [
            [
              5033,
              0
            ],
            [
              5036,
              0
            ]
          ],
          "mid": [
            [
              5034,
              1
            ]
          ]
        },
        "states": [
          "<span style=\"color:#DC6727\">7级（额外）</span>：生命增加 120000",
          "<span style=\"color:#DC6727\">8级（额外）</span>：防御力 13000 "
        ],
        "level": 3
      }
    ],
    "blackSpan": {
      "1": [],
      "2": []
    },
    "whiteSpan": {
      "1": [],
      "2": []
    }
  }
}